MANIFEST.in
README.rst
setup.py
iodata/__init__.py
iodata/cp2k.py
iodata/cube.py
iodata/gaussian.py
iodata/iodata.py
iodata/molden.py
iodata/molekel.py
iodata/molpro.py
iodata/overlap.py
iodata/overlap_accel.pyx
iodata/overlap_helper.py
iodata/periodic.py
iodata/utils.py
iodata/vasp.py
iodata/version.py
iodata/wfn.py
iodata/xyz.py
iodata.egg-info/PKG-INFO
iodata.egg-info/SOURCES.txt
iodata.egg-info/dependency_links.txt
iodata.egg-info/not-zip-safe
iodata.egg-info/requires.txt
iodata.egg-info/top_level.txt
iodata/test/__init__.py
iodata/test/common.py
iodata/test/mulliken.py
iodata/test/test_cp2k.py
iodata/test/test_cube.py
iodata/test/test_gaussian.py
iodata/test/test_iodata.py
iodata/test/test_molden.py
iodata/test/test_molekel.py
iodata/test/test_molpro.py
iodata/test/test_overlap.py
iodata/test/test_vasp.py
iodata/test/test_wfn.py
iodata/test/test_xyz.py
iodata/test/cached/2h-azirine-cc.fchk
iodata/test/cached/2h-azirine-ci.fchk
iodata/test/cached/2h-azirine-mp2.fchk
iodata/test/cached/2h-azirine-mp3.fchk
iodata/test/cached/CHGCAR.oxygen
iodata/test/cached/CHGCAR.water
iodata/test/cached/F.molden
iodata/test/cached/FCIDUMP.molpro.h2
iodata/test/cached/FCIDUMP.psi4.h2
iodata/test/cached/LOCPOT.oxygen
iodata/test/cached/POSCAR.cubicbn_cartesian
iodata/test/cached/POSCAR.cubicbn_direct
iodata/test/cached/POSCAR.water
iodata/test/cached/aelta.cube
iodata/test/cached/atom_om2.cp2k.out
iodata/test/cached/atom_si.cp2k.out
iodata/test/cached/carbon_gs_ae_contracted.cp2k.out
iodata/test/cached/carbon_gs_ae_uncontracted.cp2k.out
iodata/test/cached/carbon_gs_pp_contracted.cp2k.out
iodata/test/cached/carbon_gs_pp_uncontracted.cp2k.out
iodata/test/cached/carbon_sc_ae_contracted.cp2k.out
iodata/test/cached/carbon_sc_ae_uncontracted.cp2k.out
iodata/test/cached/carbon_sc_pp_contracted.cp2k.out
iodata/test/cached/carbon_sc_pp_uncontracted.cp2k.out
iodata/test/cached/ch3_hf_sto3g.fchk
iodata/test/cached/ch3_rohf_sto3g_g03.fchk
iodata/test/cached/ethanol.mkl
iodata/test/cached/h2_ccpvqz.wfn
iodata/test/cached/h2_sto3g.mkl
iodata/test/cached/h2o.molden.input
iodata/test/cached/h2o_sto3g.fchk
iodata/test/cached/h2o_sto3g.wfn
